gui4pygame/__init__.py
gui4pygame/gui4pygame.py
gui4pygame-0.0.2.dist-info/METADATA
gui4pygame-0.0.2.dist-info/WHEEL
gui4pygame-0.0.2.dist-info/top_level.txt
gui4pygame-0.0.2.dist-info/RECORD
